aliyunsdkddoscoo/__init__.py
aliyunsdkddoscoo/endpoint.py
aliyunsdkddoscoo/request/__init__.py
aliyunsdkddoscoo/request/v20200101/AddAutoCcBlacklistRequest.py
aliyunsdkddoscoo/request/v20200101/AddAutoCcWhitelistRequest.py
aliyunsdkddoscoo/request/v20200101/AssociateWebCertRequest.py
aliyunsdkddoscoo/request/v20200101/AttachSceneDefenseObjectRequest.py
aliyunsdkddoscoo/request/v20200101/ConfigL7RsPolicyRequest.py
aliyunsdkddoscoo/request/v20200101/ConfigLayer4RealLimitRequest.py
aliyunsdkddoscoo/request/v20200101/ConfigLayer4RemarkRequest.py
aliyunsdkddoscoo/request/v20200101/ConfigLayer4RuleBakModeRequest.py
aliyunsdkddoscoo/request/v20200101/ConfigLayer4RulePolicyRequest.py
aliyunsdkddoscoo/request/v20200101/ConfigNetworkRegionBlockRequest.py
aliyunsdkddoscoo/request/v20200101/ConfigNetworkRulesRequest.py
aliyunsdkddoscoo/request/v20200101/ConfigUdpReflectRequest.py
aliyunsdkddoscoo/request/v20200101/ConfigWebCCTemplateRequest.py
aliyunsdkddoscoo/request/v20200101/ConfigWebIpSetRequest.py
aliyunsdkddoscoo/request/v20200101/CreateAsyncTaskRequest.py
aliyunsdkddoscoo/request/v20200101/CreateDomainResourceRequest.py
aliyunsdkddoscoo/request/v20200101/CreateNetworkRulesRequest.py
aliyunsdkddoscoo/request/v20200101/CreatePortRequest.py
aliyunsdkddoscoo/request/v20200101/CreateSceneDefensePolicyRequest.py
aliyunsdkddoscoo/request/v20200101/CreateSchedulerRuleRequest.py
aliyunsdkddoscoo/request/v20200101/CreateTagResourcesRequest.py
aliyunsdkddoscoo/request/v20200101/CreateWebCCRuleRequest.py
aliyunsdkddoscoo/request/v20200101/CreateWebRuleRequest.py
aliyunsdkddoscoo/request/v20200101/DeleteAsyncTaskRequest.py
aliyunsdkddoscoo/request/v20200101/DeleteAutoCcBlacklistRequest.py
aliyunsdkddoscoo/request/v20200101/DeleteAutoCcWhitelistRequest.py
aliyunsdkddoscoo/request/v20200101/DeleteDomainResourceRequest.py
aliyunsdkddoscoo/request/v20200101/DeleteNetworkRuleRequest.py
aliyunsdkddoscoo/request/v20200101/DeletePortRequest.py
aliyun_python_sdk_ddoscoo-1.0.6.dist-info/LICENSE
aliyun_python_sdk_ddoscoo-1.0.6.dist-info/METADATA
aliyun_python_sdk_ddoscoo-1.0.6.dist-info/WHEEL
aliyun_python_sdk_ddoscoo-1.0.6.dist-info/top_level.txt
aliyun_python_sdk_ddoscoo-1.0.6.dist-info/RECORD
